shellsense/__init__.py
shellsense/__main__.py
shellsense/ai/prompts/__init__.py
shellsense/ai/prompts/instructions.py
shellsense/ai/providers/__init__.py
shellsense/ai/providers/base_provider.py
shellsense/ai/providers/cloudflare_provider.py
shellsense/ai/providers/friendly_ai_response.py
shellsense/ai/providers/gemini_provider.py
shellsense/ai/providers/openai_provider.py
shellsense/config/__init__.py
shellsense/config/example.env
shellsense/config/settings.py
shellsense/tools/__init__.py
shellsense/tools/base_tool.py
shellsense/tools/tool_manager.py
shellsense/tools/coder/code_generator.py
shellsense/tools/data/github.py
shellsense/tools/data/stock.py
shellsense/tools/data/wikipedia_search.py
shellsense/tools/language/translator.py
shellsense/tools/media/screenshoter.py
shellsense/tools/shell/command_execution.py
shellsense/tools/web/crawler.py
shellsense/tools/web/producthunt.py
shellsense/tools/web/websearch.py
shellsense/utils/__init__.py
shellsense/utils/loading.py
shellsense/utils/logging_manager.py
shellsense/utils/system_context.py
shellsense-0.1.0.dist-info/LICENSE
shellsense-0.1.0.dist-info/METADATA
shellsense-0.1.0.dist-info/WHEEL
shellsense-0.1.0.dist-info/entry_points.txt
shellsense-0.1.0.dist-info/top_level.txt
shellsense-0.1.0.dist-info/RECORD
