Metadata-Version: 2.2
Name: shellsense
Version: 0.1.0
Summary: Universal AI-powered terminal assistant for Linux
Author-email: venopyX <gladsonchala@gmail.com>
License: MIT License
Project-URL: Homepage, https://github.com/venopyX/shellsense
Project-URL: Repository, https://github.com/venopyX/shellsense.git
Project-URL: Documentation, https://github.com/venopyX/shellsense/wiki
Project-URL: Changelog, https://github.com/venopyX/shellsense/releases
Classifier: Development Status :: 4 - Beta
Classifier: Environment :: Console
Classifier: Intended Audience :: Developers
Classifier: License :: OSI Approved :: MIT License
Classifier: Operating System :: POSIX :: Linux
Classifier: Programming Language :: Python :: 3
Classifier: Programming Language :: Python :: 3.8
Classifier: Programming Language :: Python :: 3.9
Classifier: Programming Language :: Python :: 3.10
Classifier: Topic :: System :: Shells
Classifier: Topic :: Utilities
Requires-Python: >=3.8
License-File: LICENSE
Requires-Dist: python-dotenv
Requires-Dist: openai
Requires-Dist: requests
Requires-Dist: bs4
Requires-Dist: selenium
Requires-Dist: pillow
Requires-Dist: googlesearch-python
Requires-Dist: beautifulsoup4
Requires-Dist: deep_translator
Requires-Dist: googletrans
Requires-Dist: psutil
Requires-Dist: yfinance
Requires-Dist: wikipedia
Requires-Dist: requests-html
Requires-Dist: lxml[html_clean]
Requires-Dist: google-generativeai
Provides-Extra: dev
Requires-Dist: python-dotenv; extra == "dev"
Requires-Dist: openai; extra == "dev"
Requires-Dist: requests; extra == "dev"
Requires-Dist: psutil; extra == "dev"
Requires-Dist: bs4; extra == "dev"
Requires-Dist: selenium; extra == "dev"
Requires-Dist: pillow; extra == "dev"
Requires-Dist: googlesearch-python; extra == "dev"
Requires-Dist: beautifulsoup4; extra == "dev"
Requires-Dist: deep_translator; extra == "dev"
Requires-Dist: googletrans; extra == "dev"
Requires-Dist: yfinance; extra == "dev"
Requires-Dist: wikipedia; extra == "dev"
Requires-Dist: requests-html; extra == "dev"
Requires-Dist: lxml[html_clean]; extra == "dev"
Requires-Dist: google-generativeai; extra == "dev"
Requires-Dist: sphinx; extra == "dev"
Requires-Dist: sphinx-rtd-theme; extra == "dev"
